MANIFEST.in
setup.py
Name2GenderBR/GenderClassifier.py
Name2GenderBR/__init__.py
Name2GenderBR/summary.p
Name2GenderBR.egg-info/PKG-INFO
Name2GenderBR.egg-info/SOURCES.txt
Name2GenderBR.egg-info/dependency_links.txt
Name2GenderBR.egg-info/requires.txt
Name2GenderBR.egg-info/top_level.txt