Metadata-Version: 1.1
Name: Name2GenderBR
Version: 0.7
Summary: Data analysis of name and gender of Brazilian population. Enables gender definition by name.
Home-page: https://github.com/leonardoaj/name2gender-br
Author: Leonardo A. de Jesus
Author-email: leonardoaraujo@id.uff.br
License: GNU GPL v3.0
Download-URL: https://github.com/leonardoaj/name2gender-br/archive/v_01.tar.gz
Keywords: gender,genero,brazillian,brazil,censo,census
Platform: UNKNOWN
Classifier: Development Status :: 3 - Alpha
Classifier: Intended Audience :: Developers
Classifier: Topic :: Software Development :: Build Tools
Classifier: License :: OSI Approved :: GNU General Public License v3 (GPLv3)
Classifier: Programming Language :: Python :: 3
Classifier: Programming Language :: Python :: 3.4
Classifier: Programming Language :: Python :: 3.5
Classifier: Programming Language :: Python :: 3.6
